rapidocr_paddle/__init__.py
rapidocr_paddle/config.yaml
rapidocr_paddle/main.py
rapidocr_paddle/cal_rec_boxes/__init__.py
rapidocr_paddle/cal_rec_boxes/main.py
rapidocr_paddle/ch_ppocr_cls/__init__.py
rapidocr_paddle/ch_ppocr_cls/text_cls.py
rapidocr_paddle/ch_ppocr_cls/utils.py
rapidocr_paddle/ch_ppocr_det/__init__.py
rapidocr_paddle/ch_ppocr_det/text_detect.py
rapidocr_paddle/ch_ppocr_det/utils.py
rapidocr_paddle/ch_ppocr_rec/__init__.py
rapidocr_paddle/ch_ppocr_rec/ppocr_keys_v1.txt
rapidocr_paddle/ch_ppocr_rec/text_recognize.py
rapidocr_paddle/ch_ppocr_rec/utils.py
rapidocr_paddle/models/ch_PP-OCRv4_det_infer/inference.pdiparams
rapidocr_paddle/models/ch_PP-OCRv4_det_infer/inference.pdiparams.info
rapidocr_paddle/models/ch_PP-OCRv4_det_infer/inference.pdmodel
rapidocr_paddle/models/ch_PP-OCRv4_rec_infer/inference.pdiparams
rapidocr_paddle/models/ch_PP-OCRv4_rec_infer/inference.pdiparams.info
rapidocr_paddle/models/ch_PP-OCRv4_rec_infer/inference.pdmodel
rapidocr_paddle/models/ch_ppocr_mobile_v2_cls_infer/inference.pdiparams
rapidocr_paddle/models/ch_ppocr_mobile_v2_cls_infer/inference.pdiparams.info
rapidocr_paddle/models/ch_ppocr_mobile_v2_cls_infer/inference.pdmodel
rapidocr_paddle/utils/__init__.py
rapidocr_paddle/utils/infer_engine.py
rapidocr_paddle/utils/load_image.py
rapidocr_paddle/utils/logger.py
rapidocr_paddle/utils/parse_parameters.py
rapidocr_paddle/utils/process_img.py
rapidocr_paddle/utils/vis_res.py
rapidocr_paddle-1.4.5.dist-info/METADATA
rapidocr_paddle-1.4.5.dist-info/WHEEL
rapidocr_paddle-1.4.5.dist-info/entry_points.txt
rapidocr_paddle-1.4.5.dist-info/top_level.txt
rapidocr_paddle-1.4.5.dist-info/RECORD
